odoo9_addon_account_balance_reporting-9.0.1.0.5-py2.7-nspkg.pth
odoo9_addon_account_balance_reporting-9.0.1.0.5.dist-info/DESCRIPTION.rst
odoo9_addon_account_balance_reporting-9.0.1.0.5.dist-info/METADATA
odoo9_addon_account_balance_reporting-9.0.1.0.5.dist-info/RECORD
odoo9_addon_account_balance_reporting-9.0.1.0.5.dist-info/WHEEL
odoo9_addon_account_balance_reporting-9.0.1.0.5.dist-info/metadata.json
odoo9_addon_account_balance_reporting-9.0.1.0.5.dist-info/namespace_packages.txt
odoo9_addon_account_balance_reporting-9.0.1.0.5.dist-info/top_level.txt
odoo_addons/account_balance_reporting/README.rst
odoo_addons/account_balance_reporting/__init__.py
odoo_addons/account_balance_reporting/__openerp__.py
odoo_addons/account_balance_reporting/i18n/bg.po
odoo_addons/account_balance_reporting/i18n/ca.po
odoo_addons/account_balance_reporting/i18n/cs.po
odoo_addons/account_balance_reporting/i18n/es.po
odoo_addons/account_balance_reporting/i18n/es_CO.po
odoo_addons/account_balance_reporting/i18n/es_CR.po
odoo_addons/account_balance_reporting/i18n/eu.po
odoo_addons/account_balance_reporting/i18n/fr.po
odoo_addons/account_balance_reporting/i18n/gl.po
odoo_addons/account_balance_reporting/i18n/hr.po
odoo_addons/account_balance_reporting/i18n/nl.po
odoo_addons/account_balance_reporting/i18n/pl.po
odoo_addons/account_balance_reporting/i18n/pt.po
odoo_addons/account_balance_reporting/i18n/pt_BR.po
odoo_addons/account_balance_reporting/i18n/ru.po
odoo_addons/account_balance_reporting/i18n/sl.po
odoo_addons/account_balance_reporting/i18n/sv.po
odoo_addons/account_balance_reporting/i18n/tr.po
odoo_addons/account_balance_reporting/i18n/vi.po
odoo_addons/account_balance_reporting/migrations/9.0.1.0.0/post-migration.py
odoo_addons/account_balance_reporting/models/__init__.py
odoo_addons/account_balance_reporting/models/account_balance_reporting_report.py
odoo_addons/account_balance_reporting/models/account_balance_reporting_template.py
odoo_addons/account_balance_reporting/report/account_balance_reporting_reports.xml
odoo_addons/account_balance_reporting/report/report_generic.xml
odoo_addons/account_balance_reporting/security/ir.model.access.csv
odoo_addons/account_balance_reporting/static/description/icon.png
odoo_addons/account_balance_reporting/static/description/icon.svg
odoo_addons/account_balance_reporting/tests/__init__.py
odoo_addons/account_balance_reporting/tests/test_account_balance.py
